README.md
setup.py
AH22CS174/__init__.py
AH22CS174.egg-info/PKG-INFO
AH22CS174.egg-info/SOURCES.txt
AH22CS174.egg-info/dependency_links.txt
AH22CS174.egg-info/requires.txt
AH22CS174.egg-info/top_level.txt